obslog/__init__.py
obslog/api/__init__.py
obslog/api/v1/DjangoHandler.py
obslog/api/v1/WatchdogHandler.py
obslog/api/v1/__init__.py
obslog-0.1.1.dist-info/METADATA
obslog-0.1.1.dist-info/WHEEL
obslog-0.1.1.dist-info/RECORD
